embryoseg/Augmentation3D.py
embryoseg/OptimizeThreshold.py
embryoseg/SmartSeeds3D.py
embryoseg/__init__.py
embryoseg/helpers.py
embryoseg-2.2.5.dist-info/LICENSE
embryoseg-2.2.5.dist-info/METADATA
embryoseg-2.2.5.dist-info/WHEEL
embryoseg-2.2.5.dist-info/top_level.txt
embryoseg-2.2.5.dist-info/RECORD
