Metadata-Version: 2.1
Name: embryoseg
Version: 2.2.5
Summary: SmartSeed Segmentation for animal embryonic cells.
Home-page: https://github.com/kapoorlab/EmbryoSeg/
Author: Varun Kapoor Leo Guginard
Author-email: randomaccessiblekapoor@gmail.com
License: UNKNOWN
Platform: UNKNOWN
Classifier: Development Status :: 3 - Alpha
Classifier: Natural Language :: English
Classifier: License :: OSI Approved :: MIT License
Classifier: Operating System :: OS Independent
Classifier: Programming Language :: Python
Classifier: Programming Language :: Python :: 3.7
License-File: LICENSE
Requires-Dist: numpy
Requires-Dist: pandas
Requires-Dist: napari
Requires-Dist: pyqt5
Requires-Dist: natsort
Requires-Dist: scikit-image
Requires-Dist: scipy
Requires-Dist: opencv-python-headless
Requires-Dist: tifffile
Requires-Dist: matplotlib
Requires-Dist: csbdeep
Requires-Dist: stardist
